README.rst
setup.py
django_image_diet.egg-info/PKG-INFO
django_image_diet.egg-info/SOURCES.txt
django_image_diet.egg-info/dependency_links.txt
django_image_diet.egg-info/not-zip-safe
django_image_diet.egg-info/pkg-info
django_image_diet.egg-info/requires.txt
django_image_diet.egg-info/sources.txt
django_image_diet.egg-info/top_level.txt
image_diet/__init__.py
image_diet/diet.py
image_diet/file_system_storage.py
image_diet/models.py
image_diet/settings.py
image_diet/signals.py
image_diet/management/__init__.py
image_diet/management/commands/__init__.py
image_diet/management/commands/check_diet_tools.py
image_diet/management/commands/compress_remote_images.py
image_diet/management/commands/diet_images.py
image_diet/tests/__init__.py
image_diet/tests/test_commands.py
image_diet/tests/test_diet.py