Metadata-Version: 1.1
Name: django-image-diet
Version: 0.1.4.2
Summary: Remove unnecessary bytes from images
Home-page: https://github.com/ArabellaTech/django-image-diet
Author: Arabel.la
Author-email: geeks@arabel.la
License: MIT License
Platform: OS Independent
Classifier: Development Status :: 4 - Beta
Classifier: Environment :: Web Environment
Classifier: Intended Audience :: Developers
Classifier: Operating System :: OS Independent
Classifier: Programming Language :: Python :: 2.7
Classifier: Programming Language :: Python :: 3.3
Classifier: Programming Language :: Python :: 3.4
Classifier: Programming Language :: Python :: 3.5
Classifier: Framework :: Django
Classifier: Topic :: Utilities
